{"timestamp": "2020-08-13T00:11:46+00:00", "events": [{"event_id": "114639", "currency": "AUD", "impact": "Low Impact Expected", "event": "MI Leading Index m/m", "actual": "", "forecast": "", "previous": "0.4%", "event_dt": "2020-08-19T00:30:00+00:00"}, {"event_id": "112330", "currency": "GBP", "impact": "Medium Impact Expected", "event": "CPI y/y", "actual": "", "forecast": "", "previous": "0.6%", "event_dt": "2020-08-19T06:00:00+00:00"}, {"event_id": "112331", "currency": "GBP", "impact": "Low Impact Expected", "event": "Core CPI y/y", "actual": "", "forecast": "", "previous": "1.4%", "event_dt": "2020-08-19T06:00:00+00:00"}, {"event_id": "112333", "currency": "GBP", "impact": "Low Impact Expected", "event": "PPI Input m/m", "actual": "", "forecast": "", "previous": "2.4%", "event_dt": "2020-08-19T06:00:00+00:00"}, {"event_id": "112332", "currency": "GBP", "impact": "Low Impact Expected", "event": "PPI Output m/m", "actual": "", "forecast": "", "previous": "0.3%", "event_dt": "2020-08-19T06:00:00+00:00"}, {"event_id": "112335", "currency": "GBP", "impact": "Low Impact Expected", "event": "RPI y/y", "actual": "", "forecast": "", "previous": "1.1%", "event_dt": "2020-08-19T06:00:00+00:00"}, {"event_id": "112614", "currency": "EUR", "impact": "Low Impact Expected", "event": "Current Account", "actual": "", "forecast": "", "previous": "8.0B", "event_dt": "2020-08-19T08:00:00+00:00"}, {"event_id": "112334", "currency": "GBP", "impact": "Low Impact Expected", "event": "HPI y/y", "actual": "", "forecast": "", "previous": "", "event_dt": "2020-08-19T00:00:00+00:00"}, {"event_id": "112707", "currency": "EUR", "impact": "Low Impact Expected", "event": "Final CPI y/y", "actual": "", "forecast": "", "previous": "0.3%", "event_dt": "2020-08-19T09:00:00+00:00"}, {"event_id": "112706", "currency": "EUR", "impact": "Low Impact Expected", "event": "Final Core CPI y/y", "actual": "", "forecast": "", "previous": "1.2%", "event_dt": "2020-08-19T09:00:00+00:00"}, {"event_id": "112926", "currency": "EUR", "impact": "Low Impact Expected", "event": "German 30-y Bond Auction", "actual": "", "forecast": "", "previous": "-0.06|2.4", "event_dt": "2020-08-19T00:00:00+00:00"}, {"event_id": "114437", "currency": "CAD", "impact": "Low Impact Expected", "event": "CPI m/m", "actual": "", "forecast": "", "previous": "0.8%", "event_dt": "2020-08-19T12:30:00+00:00"}, {"event_id": "114435", "currency": "CAD", "impact": "Low Impact Expected", "event": "Common CPI y/y", "actual": "", "forecast": "", "previous": "1.5%", "event_dt": "2020-08-19T12:30:00+00:00"}, {"event_id": "114436", "currency": "CAD", "impact": "Low Impact Expected", "event": "Core CPI m/m", "actual": "", "forecast": "", "previous": "0.4%", "event_dt": "2020-08-19T12:30:00+00:00"}, {"event_id": "114438", "currency": "CAD", "impact": "Low Impact Expected", "event": "Median CPI y/y", "actual": "", "forecast": "", "previous": "1.9%", "event_dt": "2020-08-19T12:30:00+00:00"}, {"event_id": "114439", "currency": "CAD", "impact": "Low Impact Expected", "event": "Trimmed CPI y/y", "actual": "", "forecast": "", "previous": "1.8%", "event_dt": "2020-08-19T12:30:00+00:00"}, {"event_id": "113801", "currency": "CAD", "impact": "Low Impact Expected", "event": "Wholesale Sales m/m", "actual": "", "forecast": "", "previous": "5.7%", "event_dt": "2020-08-19T12:30:00+00:00"}, {"event_id": "110942", "currency": "USD", "impact": "Medium Impact Expected", "event": "Crude Oil Inventories", "actual": "", "forecast": "", "previous": "-4.5M", "event_dt": "2020-08-19T14:30:00+00:00"}, {"event_id": "111371", "currency": "USD", "impact": "Medium Impact Expected", "event": "FOMC Meeting Minutes", "actual": "", "forecast": "", "previous": "", "event_dt": "2020-08-19T18:00:00+00:00"}]}