{"timestamp": "2020-07-08T00:09:42+00:00", "events": [{"event_id": "113544", "currency": "NZD", "impact": "Low Impact Expected", "event": "ANZ Commodity Prices m/m", "actual": "-0.7%", "forecast": "", "previous": "1.1%", "event_dt": "2020-07-06T01:00:00+00:00"}, {"event_id": "114748", "currency": "AUD", "impact": "Low Impact Expected", "event": "MI Inflation Gauge m/m", "actual": "0.6%", "forecast": "", "previous": "-1.2%", "event_dt": "2020-07-06T01:02:00+00:00"}, {"event_id": "114578", "currency": "AUD", "impact": "Low Impact Expected", "event": "ANZ Job Advertisements m/m", "actual": "42.0%", "forecast": "", "previous": "-0.3%", "event_dt": "2020-07-06T01:30:00+00:00"}, {"event_id": "113013", "currency": "EUR", "impact": "Low Impact Expected", "event": "German Factory Orders m/m", "actual": "10.4%", "forecast": "15.1%", "previous": "-26.2%", "event_dt": "2020-07-06T06:00:00+00:00"}, {"event_id": "112868", "currency": "EUR", "impact": "Low Impact Expected", "event": "Sentix Investor Confidence", "actual": "-18.2", "forecast": "-10.8", "previous": "-24.8", "event_dt": "2020-07-06T08:30:00+00:00"}, {"event_id": "112188", "currency": "GBP", "impact": "Low Impact Expected", "event": "Construction PMI", "actual": "55.3", "forecast": "46.0", "previous": "28.9", "event_dt": "2020-07-06T08:30:00+00:00"}, {"event_id": "110754", "currency": "GBP", "impact": "Low Impact Expected", "event": "Housing Equity Withdrawal q/q", "actual": "-5.1B", "forecast": "", "previous": "-5.0B", "event_dt": "2020-07-06T08:34:00+00:00"}, {"event_id": "112635", "currency": "EUR", "impact": "Low Impact Expected", "event": "Retail Sales m/m", "actual": "17.8%", "forecast": "15.0%", "previous": "-12.1%", "event_dt": "2020-07-06T09:00:00+00:00"}, {"event_id": "111540", "currency": "USD", "impact": "Low Impact Expected", "event": "Final Services PMI", "actual": "47.9", "forecast": "47.0", "previous": "46.7", "event_dt": "2020-07-06T13:45:00+00:00"}, {"event_id": "111539", "currency": "USD", "impact": "High Impact Expected", "event": "ISM Non-Manufacturing PMI", "actual": "57.1", "forecast": "50.0", "previous": "45.4", "event_dt": "2020-07-06T14:00:00+00:00"}, {"event_id": "113657", "currency": "CAD", "impact": "Medium Impact Expected", "event": "BOC Business Outlook Survey", "actual": "", "forecast": "", "previous": "", "event_dt": "2020-07-06T14:30:00+00:00"}, {"event_id": "113375", "currency": "NZD", "impact": "Low Impact Expected", "event": "NZIER Business Confidence", "actual": "-63", "forecast": "", "previous": "-70", "event_dt": "2020-07-06T22:03:00+00:00"}, {"event_id": "112758", "currency": "AUD", "impact": "Low Impact Expected", "event": "AIG Services Index", "actual": "31.5", "forecast": "", "previous": "31.6", "event_dt": "2020-07-06T22:30:00+00:00"}, {"event_id": "115112", "currency": "JPY", "impact": "Low Impact Expected", "event": "Average Cash Earnings y/y", "actual": "-2.1%", "forecast": "-0.9%", "previous": "-0.7%", "event_dt": "2020-07-06T23:30:00+00:00"}, {"event_id": "114999", "currency": "JPY", "impact": "Low Impact Expected", "event": "Household Spending y/y", "actual": "-16.2%", "forecast": "-11.8%", "previous": "-11.1%", "event_dt": "2020-07-06T23:30:00+00:00"}]}